miniplayer/__init__.py
miniplayer-1.7.1.data/scripts/miniplayer
miniplayer-1.7.1.dist-info/LICENSE
miniplayer-1.7.1.dist-info/METADATA
miniplayer-1.7.1.dist-info/WHEEL
miniplayer-1.7.1.dist-info/top_level.txt
miniplayer-1.7.1.dist-info/RECORD
