Metadata-Version: 2.1
Name: miniplayer
Version: 1.7.1
Summary: An mpd client with album art and basic functionality.
Home-page: https://github.com/GuardKenzie/miniplayer
Author: Erica Ferrua
Author-email: tolvukisa@gmail.com
Classifier: Programming Language :: Python :: 3
Classifier: License :: OSI Approved :: MIT License
Classifier: Operating System :: OS Independent
License-File: LICENSE
Requires-Dist: python-mpd2
Requires-Dist: ffmpeg-python
Requires-Dist: pixcat
Requires-Dist: pillow
Requires-Dist: requests
Requires-Dist: ueberzug
Requires-Dist: colorthief
